LICENSE.rst
cyinstaller/__init__.py
cyinstaller/__main__.py
cyinstaller/config.py
cyinstaller/core.py
cyinstaller/log.py
cyinstaller/template.spec
cyinstaller-1.2.0.dist-info/LICENSE.rst
cyinstaller-1.2.0.dist-info/METADATA
cyinstaller-1.2.0.dist-info/WHEEL
cyinstaller-1.2.0.dist-info/entry_points.txt
cyinstaller-1.2.0.dist-info/RECORD
