Metadata-Version: 2.1
Name: CyInstaller
Version: 1.2.0
Summary: A cli tool to package application with Cython & PyInstaller.
Home-page: https://github.com/SolardiaX/CyInstaller
License: MIT
Author: SolardiaX
Author-email: solardiax@hotmail.com
Maintainer: SolardiaX
Maintainer-email: solardiax@hotmail.com
Requires-Python: >=3.8,<3.13
Classifier: Development Status :: 4 - Beta
Classifier: Environment :: Console
Classifier: Intended Audience :: Developers
Classifier: License :: OSI Approved :: BSD License
Classifier: License :: OSI Approved :: MIT License
Classifier: Operating System :: OS Independent
Classifier: Programming Language :: Python
Classifier: Programming Language :: Python :: 3
Classifier: Programming Language :: Python :: 3.8
Classifier: Programming Language :: Python :: 3.9
Classifier: Programming Language :: Python :: 3.10
Classifier: Programming Language :: Python :: 3.11
Classifier: Programming Language :: Python :: 3.12
Classifier: Topic :: Software Development
Classifier: Topic :: Software Development :: Build Tools
Classifier: Topic :: Software Development :: Compilers
Classifier: Topic :: Software Development :: Interpreters
Classifier: Topic :: Software Development :: Libraries :: Python Modules
Classifier: Topic :: System :: Installation/Setup
Classifier: Topic :: System :: Software Distribution
Classifier: Topic :: Utilities
Requires-Dist: Cython (>=3.0.10,<4.0.0)
Requires-Dist: PyYAML (>=6.0.1,<7.0.0)
Requires-Dist: click (>=8.1.7,<9.0.0)
Requires-Dist: pyinstaller (>=6.5.0,<7.0.0)
Project-URL: Repository, https://github.com/SolardiaX/CyInstaller
